{"type": "Feature", "id": 12515242, "properties": {"woe:id": 12515242, "woe:parent_id": 22723318, "woe:name": "Khuzdar Airport", "woe:placetype": 14, "woe:placetype_name": "Airport", "woe:lang": "ENG", "iso:country": "PK", "meta:provider": ["geoplanet:7.3.1", "geoplanet:7.3.2", "geoplanet:7.4.0", "geoplanet:7.4.1", "geoplanet:7.5.1", "geoplanet:7.5.2", "geoplanet:7.6.0", "geoplanet:7.8.1", "geoplanet:7.9.0", "geoplanet:7.10.0", "geoplanet:8.0.0", "woeplanet:8.0.0"], "meta:indexed": "2020-08-20T21:03:35.531677", "woe:alias_ENG_V": ["KDD Airport", "KDD"], "meta:updated": "2020-08-22T02:50:19.149077", "woe:hierarchy": {"continent": 24865671, "country": 23424922, "town": 0, "planet": 1, "county": 0, "suburb": 0, "state": 2346496, "region": 0, "localadmin": 0}, "woe:timezone_id": 28350835, "woe:hash": "tkzqhe9fx9kg", "woe:centroid": [66.645798, 27.7931], "geom:latitude": 27.7931, "geom:longitude": 66.645798, "geom:hash": "tkzqhe9fx9kg", "woe:latitude": 27.7931, "geom:centroid": [66.645798, 27.7931], "woe:longitude": 66.645798, "woe:repo": "woeplanet-airport-pk"}, "geometry": {"coordinates": [66.645798, 27.7931], "type": "Point"}}