{"type": "Feature", "id": 12515226, "properties": {"woe:id": 12515226, "woe:parent_id": 2203215, "woe:name": "Bannu Airport", "woe:placetype": 14, "woe:placetype_name": "Airport", "woe:lang": "ENG", "iso:country": "PK", "meta:provider": ["geoplanet:7.3.1", "geoplanet:7.3.2", "geoplanet:7.4.0", "geoplanet:7.4.1", "geoplanet:7.5.1", "geoplanet:7.5.2", "geoplanet:7.6.0", "geoplanet:7.8.1", "geoplanet:7.9.0", "geoplanet:7.10.0", "geoplanet:8.0.0", "woeplanet:8.0.0"], "meta:indexed": "2020-08-20T21:03:35.519312", "woe:alias_ENG_V": ["BNP Airport", "BNP"], "meta:updated": "2020-08-22T02:50:19.143492", "woe:hierarchy": {"continent": 24865671, "country": 23424922, "town": 0, "planet": 1, "county": 0, "suburb": 0, "state": 2346497, "region": 0, "localadmin": 0}, "woe:timezone_id": 28350835, "woe:hash": "ttf5sfdtpshv", "woe:centroid": [70.525002, 32.973598], "geom:latitude": 32.973598, "geom:longitude": 70.525002, "geom:hash": "ttf5sfdtpshv", "woe:latitude": 32.973598, "geom:centroid": [70.525002, 32.973598], "woe:longitude": 70.525002, "woe:repo": "woeplanet-airport-pk"}, "geometry": {"coordinates": [70.525002, 32.973598], "type": "Point"}}