{"type": "Feature", "id": 12515258, "geometry": {"type": "Point", "coordinates": [71.514999, 33.993301]}, "properties": {"woe:id": 12515258, "woe:parent_id": 2208972, "woe:name": "Peshawar Airport", "woe:placetype": 14, "woe:placetype_name": "Airport", "woe:lang": "ENG", "iso:country": "PK", "meta:provider": ["geoplanet:7.3.1", "geoplanet:7.3.2", "geoplanet:7.4.0", "geoplanet:7.4.1", "geoplanet:7.5.1", "geoplanet:7.5.2", "geoplanet:7.6.0", "geoplanet:7.8.1", "geoplanet:7.9.0", "geoplanet:7.10.0", "geoplanet:8.0.0", "woeplanet:8.0.0"], "meta:indexed": "2020-08-20T21:03:35.543440", "woe:alias_ENG_V": ["PEW Airport", "PEW"], "meta:updated": "2020-10-14T12:07:00.121008", "woe:hierarchy": {"continent": 24865671, "country": 23424922, "town": 0, "planet": 1, "county": 0, "suburb": 0, "state": 2346495, "region": 0, "localadmin": 0}, "woe:timezone_id": 28350835, "woe:hash": "tw4c7k79k684", "woe:centroid": [71.514999, 33.993301], "geom:latitude": 33.993301, "geom:longitude": 71.514999, "geom:hash": "tw4c7k79k684", "woe:latitude": 33.993301, "geom:centroid": [71.514999, 33.993301], "woe:longitude": 71.514999, "woe:repo": "woeplanet-airport-pk", "geom:area": 0.0, "woe:scale": 19}}