{"type": "Feature", "id": 12515245, "properties": {"woe:id": 12515245, "woe:parent_id": 2197142, "woe:name": "Lahore Airport", "woe:placetype": 14, "woe:placetype_name": "Airport", "woe:lang": "ENG", "iso:country": "PK", "meta:provider": ["geoplanet:7.3.1", "geoplanet:7.3.2", "geoplanet:7.4.0", "geoplanet:7.4.1", "geoplanet:7.5.1", "geoplanet:7.5.2", "geoplanet:7.6.0", "geoplanet:7.8.1", "geoplanet:7.9.0", "geoplanet:7.10.0", "geoplanet:8.0.0", "woeplanet:8.0.0"], "meta:indexed": "2020-08-20T21:03:35.533631", "woe:alias_ENG_V": ["LHE Airport", "LHE"], "meta:updated": "2020-08-22T02:50:19.150442", "woe:hierarchy": {"continent": 24865671, "country": 23424922, "town": 0, "planet": 1, "county": 0, "suburb": 0, "state": 2346498, "region": 0, "localadmin": 0}, "woe:timezone_id": 28350835, "woe:hash": "ttsgkf5wcy90", "woe:centroid": [74.393311, 31.520969], "geom:latitude": 31.520969, "geom:longitude": 74.393311, "geom:hash": "ttsgkf5wcy90", "woe:latitude": 31.520969, "geom:centroid": [74.393311, 31.520969], "woe:longitude": 74.393311, "woe:repo": "woeplanet-airport-pk"}, "geometry": {"coordinates": [74.393311, 31.520969], "type": "Point"}}